dbmaster/__init__.py
dbmaster/__main__.py
dbmaster/_version.py
dbmaster/command.py
dbmaster/config.py
dbmaster/config_example.toml
dbmaster/util.py
dbmaster/catalog/__init__.py
dbmaster/catalog/base.py
dbmaster/catalog/kline.py
dbmaster/derived/__init__.py
dbmaster/derived/base.py
dbmaster/derived/pmom.py
dbmaster/vendor/__init__.py
dbmaster/vendor/base.py
dbmaster/vendor/binance.py
dbmaster-0.2.0.dist-info/LICENSE
dbmaster-0.2.0.dist-info/METADATA
dbmaster-0.2.0.dist-info/WHEEL
dbmaster-0.2.0.dist-info/entry_points.txt
dbmaster-0.2.0.dist-info/top_level.txt
dbmaster-0.2.0.dist-info/RECORD
