Metadata-Version: 2.1
Name: dbmaster
Version: 0.2.0
Summary: Personal Quant Research Database Manager
Author-email: You Xie <xyshell@bu.edu>
Maintainer-email: You Xie <xyshell@bu.edu>
License: Copyright (c) 2024 You Xie
Project-URL: Homepage, https://github.com/xyshell/dbmaster
Keywords: quant research,personal database
Classifier: Development Status :: 4 - Beta
Classifier: Intended Audience :: Developers
Classifier: Topic :: Software Development :: Libraries :: Python Modules
Classifier: Topic :: Office/Business :: Financial :: Investment
Classifier: License :: OSI Approved :: MIT License
Classifier: Programming Language :: Python :: 3.12
Classifier: Operating System :: OS Independent
Requires-Python: >=3.12
License-File: LICENSE
Requires-Dist: numpy <2.0,>=1.26
Requires-Dist: pandas <3.0,>=2.2
Requires-Dist: pydantic <3.0,>=2.7
Requires-Dist: pydantic-settings <3.0,>=2.2
Requires-Dist: SQLAlchemy <3.0,>=2.0
Requires-Dist: fire <1.0,>=0.6.0
Requires-Dist: retry <1.0,>=0.9.2
Provides-Extra: binance
Requires-Dist: python-binance <2.0,>=1.0.19 ; extra == 'binance'
Provides-Extra: dev
Requires-Dist: pytest >=8.1 ; extra == 'dev'
Requires-Dist: ruff >=0.4 ; extra == 'dev'
Requires-Dist: build >=1.2 ; extra == 'dev'
